mastojeppetto/__init__.py
mastojeppetto/main.py
mastojeppetto-0.0.5.dist-info/LICENSE.txt
mastojeppetto-0.0.5.dist-info/METADATA
mastojeppetto-0.0.5.dist-info/WHEEL
mastojeppetto-0.0.5.dist-info/entry_points.txt
mastojeppetto-0.0.5.dist-info/top_level.txt
mastojeppetto-0.0.5.dist-info/RECORD
